Metadata-Version: 2.1
Name: hiflow
Version: 1.1
Summary: Workflow library with configurable modules
Home-page: https://git.woa.com/merlinbao/hiflow
Author: baoyuanqing
Author-email: baoyuanqing@vip.qq.com
License: MIT
Keywords: workflow
Classifier: Programming Language :: Python :: 3.6
Classifier: Programming Language :: Python :: 3.7
Classifier: Programming Language :: Python :: 3.8
Classifier: License :: OSI Approved :: MIT License
Classifier: Operating System :: OS Independent
Requires-Python: >=3.6
License-File: LICENSE
Requires-Dist: colorama (>=0.4.3)
Requires-Dist: opencv-python (>=4.5.4.60)
Requires-Dist: opencv-contrib-python (>=3.4.2.16)
